PyGPTK/__init__.py
PyGPTK/extraction.py
PyGPTK/read.py
PyGPTK-0.0.1.dist-info/LICENSE
PyGPTK-0.0.1.dist-info/METADATA
PyGPTK-0.0.1.dist-info/WHEEL
PyGPTK-0.0.1.dist-info/top_level.txt
PyGPTK-0.0.1.dist-info/RECORD
