Metadata-Version: 2.1
Name: PyGPTK
Version: 0.0.1
Summary: This repository contains Python functions for extracting gene features from a GFF3 file and performing keyword analysis using TF-IDF (Term Frequency-Inverse Document Frequency).
Author: Siddhu Pendyala
Author-email: Siddhu Pendyala <siddhu.pendyala@outlook.com>
License: 
Keywords: genome,processing,toolkit
Classifier: License :: OSI Approved :: Apache Software License
Classifier: Programming Language :: Python
Classifier: Programming Language :: Python :: 3
Requires-Python: >=3.9
License-File: LICENSE
Requires-Dist: nltk
